{
    "last_updated": "Thu, 02 May 2013 13:53:02 +0100",
    "tournaments": [
        {
            "country": "Portugal",
            "events": [
                {
                    "duration": "1:19:3",
                    "head_to_head_url": "http://legacy.tennis.com/livescores/head2head.aspx?id1=48791&id2=48195",
                    "id": "1448258",
                    "players": [
                        {
                            "country": "CH",
                            "id": "48791",
                            "is_serving": false,
                            "is_winner": false,
                            "name": "Romina Oprandia",
                            "set_games": [
                                "7"
                            ],
                            "url": "http://legacy.tennis.com/players/player_info.aspx?player_name=Romina+Oprandi"
                        },
                        {
                            "country": "RU",
                            "id": "48195",
                            "is_serving": true,
                            "is_winner": false,
                            "name": "Svetlana Kuznetsova",
                            "set_games": [
                                "5"
                            ],
                            "url": "http://legacy.tennis.com/players/player_info.aspx?player_name=Svetlana+Kuznetsova"
                        }
                    ],
                    "round": "Quarter-Final",
                    "status": "In progress"
                },
                {
                    "duration": "0:7:4",
                    "head_to_head_url": "http://legacy.tennis.com/livescores/head2head.aspx?id1=49048&id2=48663",
                    "id": "1448298",
                    "players": [
                        {
                            "country": "RU",
                            "id": "49048",
                            "is_serving": true,
                            "is_winner": null,
                            "name": "Anastasia Pavlyuchenkova",
                            "set_games": [
                                "6",
                                "0"
                            ],
                            "url": "http://legacy.tennis.com/players/player_info.aspx?player_name=Anastasia+Pavlyuchenkova"
                        },
                        {
                            "country": "RU",
                            "id": "48663",
                            "is_serving": false,
                            "is_winner": null,
                            "name": "Elena Vesnina",
                            "set_games": [
                                "3",
                                "0"
                            ],
                            "url": "http://legacy.tennis.com/players/player_info.aspx?player_name=Elena+Vesnina"
                        }
                    ],
                    "round": "Quarter-Final",
                    "status": "In progress"
                },
                {
                    "duration": "0:6:52",
                    "head_to_head_url": "http://legacy.tennis.com/livescores/head2head.aspx?id1=199207&id2=75429",
                    "id": "1448300",
                    "players": [
                        {
                            "country": "PR",
                            "id": "199207",
                            "is_serving": true,
                            "is_winner": null,
                            "name": "Monica Puig",
                            "set_games": [
                                "1"
                            ],
                            "url": "http://legacy.tennis.com/players/player_info.aspx?player_name=Monica+Puig"
                        },
                        {
                            "country": "ES",
                            "id": "75429",
                            "is_serving": false,
                            "is_winner": null,
                            "name": "Carla Suarez",
                            "set_games": [
                                "3"
                            ],
                            "url": "http://legacy.tennis.com/players/player_info.aspx?player_name=Carla+Suarez"
                        }
                    ],
                    "round": "Quarter-Final",
                    "status": "In progress"
                },
                {
                    "duration": "4:16:58",
                    "head_to_head_url": "http://legacy.tennis.com/livescores/head2head.aspx?id1=48242&id2=48836",
                    "id": "1448326",
                    "players": [
                        {
                            "country": "EE",
                            "id": "48242",
                            "is_serving": false,
                            "is_winner": null,
                            "name": "Kaia Kanepi",
                            "set_games": [],
                            "url": "http://legacy.tennis.com/players/player_info.aspx?player_name=Kaia+Kanepi"
                        },
                        {
                            "country": "JP",
                            "id": "48836",
                            "is_serving": false,
                            "is_winner": null,
                            "name": "Ayumi Morita",
                            "set_games": [],
                            "url": "http://legacy.tennis.com/players/player_info.aspx?player_name=Ayumi+Morita"
                        }
                    ],
                    "round": "Quarter-Final",
                    "status": "Not started"
                }
            ],
            "gender": "female",
            "id": "829730",
            "location": "Oeiras",
            "name": "Portugal Open female",
            "slug": "portugal-open-female",
            "surface": "Clay"
        },
        {
            "country": "Portugal",
            "events": [
                {
                    "duration": "0:6:53",
                    "head_to_head_url": "http://legacy.tennis.com/livescores/head2head.aspx?id1=48878&id2=48597",
                    "id": "1447752",
                    "players": [
                        {
                            "country": "IT",
                            "id": "48878",
                            "is_serving": false,
                            "is_winner": null,
                            "name": "Andreas Seppi",
                            "set_games": [],
                            "url": "http://legacy.tennis.com/players/player_info.aspx?player_name=Andreas+Seppi"
                        },
                        {
                            "country": "CO",
                            "id": "48597",
                            "is_serving": false,
                            "is_winner": null,
                            "name": "Alejandro Falla",
                            "set_games": [],
                            "url": "http://legacy.tennis.com/players/player_info.aspx?player_name=Alejandro+Falla"
                        }
                    ],
                    "round": "Round of 16",
                    "status": "Not started"
                },
                {
                    "duration": "1:51:53",
                    "head_to_head_url": "http://legacy.tennis.com/livescores/head2head.aspx?id1=72276&id2=48478",
                    "id": "1447761",
                    "players": [
                        {
                            "country": "ES",
                            "id": "72276",
                            "is_serving": false,
                            "is_winner": null,
                            "name": "Albert Ramos",
                            "set_games": [],
                            "url": "http://legacy.tennis.com/players/player_info.aspx?player_name=Albert+Ramos"
                        },
                        {
                            "country": "CH",
                            "id": "48478",
                            "is_serving": false,
                            "is_winner": null,
                            "name": "Stanislas Wawrinka",
                            "set_games": [],
                            "url": "http://legacy.tennis.com/players/player_info.aspx?player_name=Stanislas+Wawrinka"
                        }
                    ],
                    "round": "Round of 16",
                    "status": "Not started"
                },
                {
                    "duration": "2:41:53",
                    "head_to_head_url": "http://legacy.tennis.com/livescores/head2head.aspx?id1=48962&id2=47997",
                    "id": "1447833",
                    "players": [
                        {
                            "country": "NL",
                            "id": "48962",
                            "is_serving": false,
                            "is_winner": null,
                            "name": "Robin Haase",
                            "set_games": [],
                            "url": "http://legacy.tennis.com/players/player_info.aspx?player_name=Robin+Haase"
                        },
                        {
                            "country": "ES",
                            "id": "47997",
                            "is_serving": false,
                            "is_winner": null,
                            "name": "Tommy Robredo",
                            "set_games": [],
                            "url": "http://legacy.tennis.com/players/player_info.aspx?player_name=Tommy+Robredo"
                        }
                    ],
                    "round": "Round of 16",
                    "status": "Not started"
                },
                {
                    "duration": "3:51:53",
                    "head_to_head_url": "http://legacy.tennis.com/livescores/head2head.aspx?id1=48940&id2=48848",
                    "id": "1447846",
                    "players": [
                        {
                            "country": "PT",
                            "id": "48940",
                            "is_serving": false,
                            "is_winner": null,
                            "name": "Gastao Elias",
                            "set_games": [],
                            "url": "http://legacy.tennis.com/players/player_info.aspx?player_name=Gastao+Elias"
                        },
                        {
                            "country": "UZ",
                            "id": "48848",
                            "is_serving": false,
                            "is_winner": null,
                            "name": "Denis Istomin",
                            "set_games": [],
                            "url": "http://legacy.tennis.com/players/player_info.aspx?player_name=Denis+Istomin"
                        }
                    ],
                    "round": "Round of 16",
                    "status": "Not started"
                }
            ],
            "gender": "male",
            "id": "829724",
            "location": "Oeiras",
            "name": "Portugal Open male",
            "slug": "portugal-open-male",
            "surface": "Clay"
        },
        {
            "country": "Germany",
            "events": [
                {
                    "duration": "4:55:40",
                    "head_to_head_url": "http://legacy.tennis.com/livescores/head2head.aspx?id1=49053&id2=47648",
                    "id": "1447619",
                    "players": [
                        {
                            "country": "LV",
                            "id": "49053",
                            "is_serving": false,
                            "is_winner": null,
                            "name": "Ernests Gulbis",
                            "set_games": [],
                            "url": "http://legacy.tennis.com/players/player_info.aspx?player_name=Ernests+Gulbis"
                        },
                        {
                            "country": "DE",
                            "id": "47648",
                            "is_serving": false,
                            "is_winner": null,
                            "name": "Tommy Haas",
                            "set_games": [],
                            "url": "http://legacy.tennis.com/players/player_info.aspx?player_name=Tommy+Haas"
                        }
                    ],
                    "round": "Round of 16",
                    "status": "Not started"
                },
                {
                    "duration": "3:10:40",
                    "head_to_head_url": "http://legacy.tennis.com/livescores/head2head.aspx?id1=48497&id2=69578",
                    "id": "1447685",
                    "players": [
                        {
                            "country": "CS",
                            "id": "48497",
                            "is_serving": false,
                            "is_winner": null,
                            "name": "Janko Tipsarevic",
                            "set_games": [],
                            "url": "http://legacy.tennis.com/players/player_info.aspx?player_name=Janko+Tipsarevic"
                        },
                        {
                            "country": "SI",
                            "id": "69578",
                            "is_serving": false,
                            "is_winner": null,
                            "name": "Grega Zemlja",
                            "set_games": [],
                            "url": "http://legacy.tennis.com/players/player_info.aspx?player_name=Grega+Zemlja"
                        }
                    ],
                    "round": "Round of 16",
                    "status": "Not started"
                },
                {
                    "duration": "1:39:20",
                    "head_to_head_url": "http://legacy.tennis.com/livescores/head2head.aspx?id1=48548&id2=106901",
                    "id": "1447816",
                    "players": [
                        {
                            "country": "DE",
                            "id": "48548",
                            "is_serving": false,
                            "is_winner": true,
                            "name": "Florian Mayer",
                            "set_games": [
                                "2",
                                "6",
                                "6"
                            ],
                            "url": "http://legacy.tennis.com/players/player_info.aspx?player_name=Florian+Mayer"
                        },
                        {
                            "country": "AU",
                            "id": "106901",
                            "is_serving": false,
                            "is_winner": false,
                            "name": "Marinko Matosevic",
                            "set_games": [
                                "6",
                                "4",
                                "2"
                            ],
                            "url": "http://legacy.tennis.com/players/player_info.aspx?player_name=Marinko+Matosevic"
                        }
                    ],
                    "round": "Round of 16",
                    "status": "Finished"
                },
                {
                    "duration": "1:20:40",
                    "head_to_head_url": "http://legacy.tennis.com/livescores/head2head.aspx?id1=49151&id2=48653",
                    "id": "1447842",
                    "players": [
                        {
                            "country": "DE",
                            "id": "49151",
                            "is_serving": false,
                            "is_winner": null,
                            "name": "Daniel Brands",
                            "set_games": [],
                            "url": "http://legacy.tennis.com/players/player_info.aspx?player_name=Daniel+Brands"
                        },
                        {
                            "country": "FR",
                            "id": "48653",
                            "is_serving": false,
                            "is_winner": null,
                            "name": "Gael Monfils",
                            "set_games": [],
                            "url": "http://legacy.tennis.com/players/player_info.aspx?player_name=Gael+Monfils"
                        }
                    ],
                    "round": "Round of 16",
                    "status": "Not started"
                }
            ],
            "gender": "male",
            "id": "829726",
            "location": "Munich",
            "name": "BMW Open male",
            "slug": "bmw-open-male",
            "surface": "Clay"
        },
        {
            "country": "United States",
            "events": [
                {
                    "duration": "22:8:26",
                    "head_to_head_url": "http://legacy.tennis.com/livescores/head2head.aspx?id1=48624&id2=56898",
                    "id": "1448328",
                    "players": [
                        {
                            "country": "US",
                            "id": "48624",
                            "is_serving": false,
                            "is_winner": null,
                            "name": "Alex Kuznetsov",
                            "set_games": [],
                            "url": "http://legacy.tennis.com/players/player_info.aspx?player_name=Alex+Kuznetsov"
                        },
                        {
                            "country": "US",
                            "id": "56898",
                            "is_serving": false,
                            "is_winner": null,
                            "name": "Tim Smyczek",
                            "set_games": [],
                            "url": "http://legacy.tennis.com/players/player_info.aspx?player_name=Tim+Smyczek"
                        }
                    ],
                    "round": "Quarter-Final",
                    "status": "Not started"
                },
                {
                    "duration": "5:8:26",
                    "head_to_head_url": "http://legacy.tennis.com/livescores/head2head.aspx?id1=48732&id2=119011",
                    "id": "1448380",
                    "players": [
                        {
                            "country": "US",
                            "id": "48732",
                            "is_serving": false,
                            "is_winner": null,
                            "name": "Donald Young",
                            "set_games": [],
                            "url": "http://legacy.tennis.com/players/player_info.aspx?player_name=Donald+Young"
                        },
                        {
                            "country": "US",
                            "id": "119011",
                            "is_serving": false,
                            "is_winner": null,
                            "name": "Ryan Harrison",
                            "set_games": [],
                            "url": "http://legacy.tennis.com/players/player_info.aspx?player_name=Ryan+Harrison"
                        }
                    ],
                    "round": "Quarter-Final",
                    "status": "Not started"
                },
                {
                    "duration": "6:53:26",
                    "head_to_head_url": "http://legacy.tennis.com/livescores/head2head.aspx?id1=148103&id2=195268",
                    "id": "1448383",
                    "players": [
                        {
                            "country": "US",
                            "id": "148103",
                            "is_serving": false,
                            "is_winner": null,
                            "name": "Denis Kudla",
                            "set_games": [],
                            "url": "http://legacy.tennis.com/players/player_info.aspx?player_name=Denis+Kudla"
                        },
                        {
                            "country": "AR",
                            "id": "195268",
                            "is_serving": false,
                            "is_winner": null,
                            "name": "Facundo Arguello",
                            "set_games": [],
                            "url": "http://legacy.tennis.com/players/player_info.aspx?player_name=Facundo+Arguello"
                        }
                    ],
                    "round": "Quarter-Final",
                    "status": "Not started"
                },
                {
                    "duration": "7:47:56",
                    "head_to_head_url": "http://legacy.tennis.com/livescores/head2head.aspx?id1=131120&id2=48336",
                    "id": "1448397",
                    "players": [
                        {
                            "country": "DE",
                            "id": "131120",
                            "is_serving": false,
                            "is_winner": null,
                            "name": "Cedrik-Marcel Stebe",
                            "set_games": [],
                            "url": "http://legacy.tennis.com/players/player_info.aspx?player_name=Cedrik-Marcel+Stebe"
                        },
                        {
                            "country": "CA",
                            "id": "48336",
                            "is_serving": false,
                            "is_winner": null,
                            "name": "Frank Dancevic",
                            "set_games": [],
                            "url": "http://legacy.tennis.com/players/player_info.aspx?player_name=Frank+Dancevic"
                        }
                    ],
                    "round": "Quarter-Final",
                    "status": "Not started"
                }
            ],
            "gender": "male",
            "id": "830575",
            "location": "Tallahassee",
            "name": "Tallahassee male",
            "slug": "tallahassee-male",
            "surface": "Clay"
        },
        {
            "country": "Tunisia",
            "events": [
                {
                    "duration": "3:56:16",
                    "head_to_head_url": "http://legacy.tennis.com/livescores/head2head.aspx?id1=48892&id2=154432",
                    "id": "1447757",
                    "players": [
                        {
                            "country": "IT",
                            "id": "48892",
                            "is_serving": false,
                            "is_winner": null,
                            "name": "Flavio Cipolla",
                            "set_games": [],
                            "url": "http://legacy.tennis.com/players/player_info.aspx?player_name=Flavio+Cipolla"
                        },
                        {
                            "country": "UA",
                            "id": "154432",
                            "is_serving": false,
                            "is_winner": null,
                            "name": "Oleksandr Nedovyesov",
                            "set_games": [],
                            "url": "http://legacy.tennis.com/players/player_info.aspx?player_name=Oleksandr+Nedovyesov"
                        }
                    ],
                    "round": "Round of 16",
                    "status": "Not started"
                },
                {
                    "duration": "3:41:16",
                    "head_to_head_url": "http://legacy.tennis.com/livescores/head2head.aspx?id1=48909&id2=48633",
                    "id": "1447774",
                    "players": [
                        {
                            "country": "ES",
                            "id": "48909",
                            "is_serving": false,
                            "is_winner": null,
                            "name": "Marcel Granollers",
                            "set_games": [],
                            "url": "http://legacy.tennis.com/players/player_info.aspx?player_name=Marcel+Granollers"
                        },
                        {
                            "country": "DZ",
                            "id": "48633",
                            "is_serving": false,
                            "is_winner": null,
                            "name": "Lamine Ouahab",
                            "set_games": [],
                            "url": "http://legacy.tennis.com/players/player_info.aspx?player_name=Lamine+Ouahab"
                        }
                    ],
                    "round": "Round of 16",
                    "status": "Not started"
                },
                {
                    "duration": "0:8:10",
                    "head_to_head_url": "http://legacy.tennis.com/livescores/head2head.aspx?id1=48390&id2=88982",
                    "id": "1447820",
                    "players": [
                        {
                            "country": "FR",
                            "id": "48390",
                            "is_serving": true,
                            "is_winner": null,
                            "name": "Florent Serra",
                            "set_games": [],
                            "url": "http://legacy.tennis.com/players/player_info.aspx?player_name=Florent+Serra"
                        },
                        {
                            "country": "IT",
                            "id": "88982",
                            "is_serving": false,
                            "is_winner": null,
                            "name": "Riccardo Ghedin",
                            "set_games": [],
                            "url": "http://legacy.tennis.com/players/player_info.aspx?player_name=Riccardo+Ghedin"
                        }
                    ],
                    "round": "Round of 16",
                    "status": "In progress"
                },
                {
                    "duration": "1:51:8",
                    "head_to_head_url": "http://legacy.tennis.com/livescores/head2head.aspx?id1=78329&id2=239220",
                    "id": "1447834",
                    "players": [
                        {
                            "country": "ES",
                            "id": "78329",
                            "is_serving": false,
                            "is_winner": null,
                            "name": "Adrian Menendez",
                            "set_games": [],
                            "url": "http://legacy.tennis.com/players/player_info.aspx?player_name=Adrian+Menendez"
                        },
                        {
                            "country": "AR",
                            "id": "239220",
                            "is_serving": true,
                            "is_winner": null,
                            "name": "Diego Sebastian Schwartzman",
                            "set_games": [],
                            "url": "http://legacy.tennis.com/players/player_info.aspx?player_name=Diego+Sebastian+Schwartzman"
                        }
                    ],
                    "round": "Round of 16",
                    "status": "In progress"
                }
            ],
            "gender": "male",
            "id": "830593",
            "location": "Tunis",
            "name": "Tunis male",
            "slug": "tunis-male",
            "surface": "Clay"
        },
        {
            "country": "Czech Republic",
            "events": [
                {
                    "duration": "4:42:18",
                    "head_to_head_url": "http://legacy.tennis.com/livescores/head2head.aspx?id1=48619&id2=48894",
                    "id": "1447687",
                    "players": [
                        {
                            "country": "CZ",
                            "id": "48619",
                            "is_serving": false,
                            "is_winner": null,
                            "name": "Ivo Minar",
                            "set_games": [],
                            "url": "http://legacy.tennis.com/players/player_info.aspx?player_name=Ivo+Minar"
                        },
                        {
                            "country": "BE",
                            "id": "48894",
                            "is_serving": false,
                            "is_winner": null,
                            "name": "Steve Darcis",
                            "set_games": [],
                            "url": "http://legacy.tennis.com/players/player_info.aspx?player_name=Steve+Darcis"
                        }
                    ],
                    "round": "Round of 16",
                    "status": "Not started"
                },
                {
                    "duration": "23:54:28",
                    "head_to_head_url": "http://legacy.tennis.com/livescores/head2head.aspx?id1=201018&id2=48785",
                    "id": "1447832",
                    "players": [
                        {
                            "country": "CZ",
                            "id": "201018",
                            "is_serving": false,
                            "is_winner": null,
                            "name": "Jiri Vesely",
                            "set_games": [],
                            "url": "http://legacy.tennis.com/players/player_info.aspx?player_name=Jiri+Vesely"
                        },
                        {
                            "country": "CZ",
                            "id": "48785",
                            "is_serving": true,
                            "is_winner": null,
                            "name": "Jaroslav Pospisil",
                            "set_games": [],
                            "url": "http://legacy.tennis.com/players/player_info.aspx?player_name=Jaroslav+Pospisil"
                        }
                    ],
                    "round": "Round of 16",
                    "status": "In progress"
                },
                {
                    "duration": "2:57:18",
                    "head_to_head_url": "http://legacy.tennis.com/livescores/head2head.aspx?id1=48670&id2=118475",
                    "id": "1448135",
                    "players": [
                        {
                            "country": "CZ",
                            "id": "48670",
                            "is_serving": false,
                            "is_winner": null,
                            "name": "Jan Hajek",
                            "set_games": [],
                            "url": "http://legacy.tennis.com/players/player_info.aspx?player_name=Jan+Hajek"
                        },
                        {
                            "country": "BA",
                            "id": "118475",
                            "is_serving": false,
                            "is_winner": null,
                            "name": "Aldin Setkic",
                            "set_games": [],
                            "url": "http://legacy.tennis.com/players/player_info.aspx?player_name=Aldin+Setkic"
                        }
                    ],
                    "round": "Round of 16",
                    "status": "Not started"
                },
                {
                    "duration": "23:57:25",
                    "head_to_head_url": "http://legacy.tennis.com/livescores/head2head.aspx?id1=48995&id2=48586",
                    "id": "1448149",
                    "players": [
                        {
                            "country": "AT",
                            "id": "48995",
                            "is_serving": true,
                            "is_winner": null,
                            "name": "Andreas Haider-Maurer",
                            "set_games": [],
                            "url": "http://legacy.tennis.com/players/player_info.aspx?player_name=Andreas+Haider-Maurer"
                        },
                        {
                            "country": "RU",
                            "id": "48586",
                            "is_serving": false,
                            "is_winner": null,
                            "name": "Teymuraz Gabashvili",
                            "set_games": [],
                            "url": "http://legacy.tennis.com/players/player_info.aspx?player_name=Teymuraz+Gabashvili"
                        }
                    ],
                    "round": "Round of 16",
                    "status": "In progress"
                }
            ],
            "gender": "male",
            "id": "830595",
            "location": "Ostrava",
            "name": "Ostrava male",
            "slug": "ostrava-male",
            "surface": "Clay"
        },
        {
            "country": "China",
            "events": [
                {
                    "duration": "1:16:20",
                    "head_to_head_url": "http://legacy.tennis.com/livescores/head2head.aspx?id1=172957&id2=204450",
                    "id": "1447538",
                    "players": [
                        {
                            "country": "LT",
                            "id": "172957",
                            "is_serving": false,
                            "is_winner": false,
                            "name": "Laurynas Grigelis",
                            "set_games": [
                                "1",
                                "4"
                            ],
                            "url": "http://legacy.tennis.com/players/player_info.aspx?player_name=Laurynas+Grigelis"
                        },
                        {
                            "country": "HU",
                            "id": "204450",
                            "is_serving": false,
                            "is_winner": true,
                            "name": "Marton Fucsovics",
                            "set_games": [
                                "6",
                                "6"
                            ],
                            "url": "http://legacy.tennis.com/players/player_info.aspx?player_name=Marton+Fucsovics"
                        }
                    ],
                    "round": "Round of 16",
                    "status": "Finished"
                },
                {
                    "duration": "1:5:25",
                    "head_to_head_url": "http://legacy.tennis.com/livescores/head2head.aspx?id1=106900&id2=48481",
                    "id": "1447543",
                    "players": [
                        {
                            "country": "AU",
                            "id": "106900",
                            "is_serving": false,
                            "is_winner": true,
                            "name": "Matthew Ebden",
                            "set_games": [
                                "6",
                                "6"
                            ],
                            "url": "http://legacy.tennis.com/players/player_info.aspx?player_name=Matthew+Ebden"
                        },
                        {
                            "country": "AU",
                            "id": "48481",
                            "is_serving": false,
                            "is_winner": false,
                            "name": "Chris Guccione",
                            "set_games": [
                                "4",
                                "4"
                            ],
                            "url": "http://legacy.tennis.com/players/player_info.aspx?player_name=Chris+Guccione"
                        }
                    ],
                    "round": "Round of 16",
                    "status": "Finished"
                },
                {
                    "duration": "4:55:45",
                    "head_to_head_url": "http://legacy.tennis.com/livescores/head2head.aspx?id1=231576&id2=72622",
                    "id": "1447913",
                    "players": [
                        {
                            "country": "CS",
                            "id": "231576",
                            "is_serving": false,
                            "is_winner": null,
                            "name": "Danilo Petrovic",
                            "set_games": [],
                            "url": "http://legacy.tennis.com/players/player_info.aspx?player_name=Danilo+Petrovic"
                        },
                        {
                            "country": "GB",
                            "id": "72622",
                            "is_serving": false,
                            "is_winner": null,
                            "name": "James Ward",
                            "set_games": [],
                            "url": "http://legacy.tennis.com/players/player_info.aspx?player_name=James+Ward"
                        }
                    ],
                    "round": "Quarter-Final",
                    "status": "Not started"
                },
                {
                    "duration": "4:55:45",
                    "head_to_head_url": "http://legacy.tennis.com/livescores/head2head.aspx?id1=106493&id2=67218",
                    "id": "1447941",
                    "players": [
                        {
                            "country": "TW",
                            "id": "106493",
                            "is_serving": false,
                            "is_winner": null,
                            "name": "Tsung-Hua Yang",
                            "set_games": [],
                            "url": "http://legacy.tennis.com/players/player_info.aspx?player_name=Tsung-Hua+Yang"
                        },
                        {
                            "country": "JP",
                            "id": "67218",
                            "is_serving": false,
                            "is_winner": null,
                            "name": "Tatsuma Ito",
                            "set_games": [],
                            "url": "http://legacy.tennis.com/players/player_info.aspx?player_name=Tatsuma+Ito"
                        }
                    ],
                    "round": "Quarter-Final",
                    "status": "Not started"
                },
                {
                    "duration": "6:40:44",
                    "head_to_head_url": "http://legacy.tennis.com/livescores/head2head.aspx?id1=186023&id2=204450",
                    "id": "1448411",
                    "players": [
                        {
                            "country": "CN",
                            "id": "186023",
                            "is_serving": false,
                            "is_winner": null,
                            "name": "Ze Zhang",
                            "set_games": [],
                            "url": "http://legacy.tennis.com/players/player_info.aspx?player_name=Ze+Zhang"
                        },
                        {
                            "country": "HU",
                            "id": "204450",
                            "is_serving": false,
                            "is_winner": null,
                            "name": "Marton Fucsovics",
                            "set_games": [],
                            "url": "http://legacy.tennis.com/players/player_info.aspx?player_name=Marton+Fucsovics"
                        }
                    ],
                    "round": "Quarter-Final",
                    "status": "Not started"
                },
                {
                    "duration": "6:40:45",
                    "head_to_head_url": "http://legacy.tennis.com/livescores/head2head.aspx?id1=106900&id2=208328",
                    "id": "1448414",
                    "players": [
                        {
                            "country": "AU",
                            "id": "106900",
                            "is_serving": false,
                            "is_winner": null,
                            "name": "Matthew Ebden",
                            "set_games": [],
                            "url": "http://legacy.tennis.com/players/player_info.aspx?player_name=Matthew+Ebden"
                        },
                        {
                            "country": "HR",
                            "id": "208328",
                            "is_serving": false,
                            "is_winner": null,
                            "name": "Dino Marcan",
                            "set_games": [],
                            "url": "http://legacy.tennis.com/players/player_info.aspx?player_name=Dino+Marcan"
                        }
                    ],
                    "round": "Quarter-Final",
                    "status": "Not started"
                }
            ],
            "gender": "male",
            "id": "830599",
            "location": "An-Ning",
            "name": "An-Ning male",
            "slug": "an-ning-male",
            "surface": "Clay"
        },
        {
            "country": "Italy",
            "events": [
                {
                    "duration": "0:4:50",
                    "head_to_head_url": "http://legacy.tennis.com/livescores/head2head.aspx?id1=186133&id2=62387",
                    "id": "1447609",
                    "players": [
                        {
                            "country": "BE",
                            "id": "186133",
                            "is_serving": true,
                            "is_winner": null,
                            "name": "Arthur de Greef",
                            "set_games": [],
                            "url": "http://legacy.tennis.com/players/player_info.aspx?player_name=Arthur+de+Greef"
                        },
                        {
                            "country": "FR",
                            "id": "62387",
                            "is_serving": false,
                            "is_winner": null,
                            "name": "Adrian Mannarino",
                            "set_games": [],
                            "url": "http://legacy.tennis.com/players/player_info.aspx?player_name=Adrian+Mannarino"
                        }
                    ],
                    "round": "Round of 16",
                    "status": "In progress"
                },
                {
                    "duration": "0:13:51",
                    "head_to_head_url": "http://legacy.tennis.com/livescores/head2head.aspx?id1=49142&id2=48867",
                    "id": "1447730",
                    "players": [
                        {
                            "country": "DE",
                            "id": "49142",
                            "is_serving": false,
                            "is_winner": null,
                            "name": "Bastian Knittel",
                            "set_games": [],
                            "url": "http://legacy.tennis.com/players/player_info.aspx?player_name=Bastian+Knittel"
                        },
                        {
                            "country": "FR",
                            "id": "48867",
                            "is_serving": true,
                            "is_winner": null,
                            "name": "David Guez",
                            "set_games": [],
                            "url": "http://legacy.tennis.com/players/player_info.aspx?player_name=David+Guez"
                        }
                    ],
                    "round": "Round of 16",
                    "status": "In progress"
                },
                {
                    "duration": "1:58:33",
                    "head_to_head_url": "http://legacy.tennis.com/livescores/head2head.aspx?id1=278476&id2=127750",
                    "id": "1447772",
                    "players": [
                        {
                            "country": "IT",
                            "id": "278476",
                            "is_serving": false,
                            "is_winner": null,
                            "name": "Riccardo Bellotti",
                            "set_games": [],
                            "url": "http://legacy.tennis.com/players/player_info.aspx?player_name=Riccardo+Bellotti"
                        },
                        {
                            "country": "FR",
                            "id": "127750",
                            "is_serving": false,
                            "is_winner": null,
                            "name": "Jonathan Dasnieres De Veigy",
                            "set_games": [],
                            "url": "http://legacy.tennis.com/players/player_info.aspx?player_name=Jonathan+Dasnieres+De+Veigy"
                        }
                    ],
                    "round": "Round of 16",
                    "status": "Not started"
                },
                {
                    "duration": "3:13:33",
                    "head_to_head_url": "http://legacy.tennis.com/livescores/head2head.aspx?id1=75637&id2=95510",
                    "id": "1448151",
                    "players": [
                        {
                            "country": "SI",
                            "id": "75637",
                            "is_serving": false,
                            "is_winner": null,
                            "name": "Blaz Kavcic",
                            "set_games": [],
                            "url": "http://legacy.tennis.com/players/player_info.aspx?player_name=Blaz+Kavcic"
                        },
                        {
                            "country": "IT",
                            "id": "95510",
                            "is_serving": false,
                            "is_winner": null,
                            "name": "Alessandro Giannessi",
                            "set_games": [],
                            "url": "http://legacy.tennis.com/players/player_info.aspx?player_name=Alessandro+Giannessi"
                        }
                    ],
                    "round": "Round of 16",
                    "status": "Not started"
                }
            ],
            "gender": "male",
            "id": "830690",
            "location": "Napoli",
            "name": "Napoli male",
            "slug": "napoli-male",
            "surface": "Clay"
        },
        {
            "country": "South Africa",
            "events": [
                {
                    "duration": "1:54:28",
                    "head_to_head_url": "http://legacy.tennis.com/livescores/head2head.aspx?id1=277121&id2=48340",
                    "id": "1448145",
                    "players": [
                        {
                            "country": "HR",
                            "id": "277121",
                            "is_serving": false,
                            "is_winner": true,
                            "name": "Mate Pavic",
                            "set_games": [
                                "7",
                                "7"
                            ],
                            "url": "http://legacy.tennis.com/players/player_info.aspx?player_name=Mate+Pavic"
                        },
                        {
                            "country": "US",
                            "id": "48340",
                            "is_serving": false,
                            "is_winner": false,
                            "name": "Rajeev Ram",
                            "set_games": [
                                "6",
                                "5"
                            ],
                            "url": "http://legacy.tennis.com/players/player_info.aspx?player_name=Rajeev+Ram"
                        }
                    ],
                    "round": "Quarter-Final",
                    "status": "Finished"
                },
                {
                    "duration": "0:6:20",
                    "head_to_head_url": "http://legacy.tennis.com/livescores/head2head.aspx?id1=48461&id2=92843",
                    "id": "1448168",
                    "players": [
                        {
                            "country": "ZA",
                            "id": "48461",
                            "is_serving": false,
                            "is_winner": null,
                            "name": "Rik De Voest",
                            "set_games": [],
                            "url": "http://legacy.tennis.com/players/player_info.aspx?player_name=Rik+De+Voest"
                        },
                        {
                            "country": "CA",
                            "id": "92843",
                            "is_serving": true,
                            "is_winner": null,
                            "name": "Vasek Pospisil",
                            "set_games": [],
                            "url": "http://legacy.tennis.com/players/player_info.aspx?player_name=Vasek+Pospisil"
                        }
                    ],
                    "round": "Quarter-Final",
                    "status": "In progress"
                },
                {
                    "duration": "1:3:37",
                    "head_to_head_url": "http://legacy.tennis.com/livescores/head2head.aspx?id1=48667&id2=341372",
                    "id": "1448171",
                    "players": [
                        {
                            "country": "SK",
                            "id": "48667",
                            "is_serving": false,
                            "is_winner": null,
                            "name": "Lukas Lacko",
                            "set_games": [],
                            "url": "http://legacy.tennis.com/players/player_info.aspx?player_name=Lukas+Lacko"
                        },
                        {
                            "country": "ZA",
                            "id": "341372",
                            "is_serving": false,
                            "is_winner": null,
                            "name": "Dean O'Brien",
                            "set_games": [],
                            "url": "http://legacy.tennis.com/players/player_info.aspx?player_name=Dean+O'Brien"
                        }
                    ],
                    "round": "Quarter-Final",
                    "status": "Not started"
                },
                {
                    "duration": "1:7:36",
                    "head_to_head_url": "http://legacy.tennis.com/livescores/head2head.aspx?id1=48617&id2=48480",
                    "id": "1448259",
                    "players": [
                        {
                            "country": "PL",
                            "id": "48617",
                            "is_serving": false,
                            "is_winner": true,
                            "name": "Michal Przysiezny",
                            "set_games": [
                                "6",
                                "7"
                            ],
                            "url": "http://legacy.tennis.com/players/player_info.aspx?player_name=Michal+Przysiezny"
                        },
                        {
                            "country": "JM",
                            "id": "48480",
                            "is_serving": false,
                            "is_winner": false,
                            "name": "Dustin Brown",
                            "set_games": [
                                "3",
                                "6"
                            ],
                            "url": "http://legacy.tennis.com/players/player_info.aspx?player_name=Dustin+Brown"
                        }
                    ],
                    "round": "Quarter-Final",
                    "status": "Finished"
                }
            ],
            "gender": "male",
            "id": "830698",
            "location": "Johannesburg",
            "name": "Johannesburg male",
            "slug": "johannesburg-male",
            "surface": "Hard"
        }
    ]
}